textdraw-0.2.2.dist-info/METADATA
textdraw-0.2.2.dist-info/WHEEL
textdraw-0.2.2.dist-info/licenses/LICENSE-APACHE
textdraw-0.2.2.dist-info/licenses/LICENSE-MIT
textdraw.libs/libgcc_s-b5472b99.so.1
textdraw/__init__.py
textdraw/__init__.pyi
textdraw/textdraw.pypy39-pp73-x86-linux-gnu.so
textdraw-0.2.2.dist-info/RECORD
