Metadata-Version: 2.4
Name: textdraw
Version: 0.2.2
Classifier: Programming Language :: Rust
Classifier: Programming Language :: Python :: Implementation :: CPython
Classifier: Programming Language :: Python :: Implementation :: PyPy
Classifier: Development Status :: 3 - Alpha
Classifier: Programming Language :: Python :: 3.8
Classifier: Programming Language :: Python :: 3.9
Classifier: Programming Language :: Python :: 3.10
Classifier: Programming Language :: Python :: 3.11
Classifier: Programming Language :: Python :: 3.12
Classifier: Programming Language :: Python :: 3.13
Classifier: Programming Language :: Python :: 3.14
Requires-Dist: pytest ; extra == 'tests'
Provides-Extra: tests
License-File: LICENSE-APACHE
License-File: LICENSE-MIT
Summary: A small tool for drawing boxes and lines on the terminal
Keywords: text,rich,drawing,terminal,ascii,unicode,graph
Author-email: Dene Hoffman <denehoffman@me.com>
Requires-Python: >=3.8
Project-URL: Homepage, https://github.com/denehoffman/textdraw
Project-URL: Repository, https://github.com/denehoffman/textdraw
Project-URL: Issues, https://github.com/denehoffman/textdraw/issues
